bass_model_package/__init__.py
bass_model_package/bass_model_package.py
bass_model_package-0.1.0.dist-info/AUTHORS.rst
bass_model_package-0.1.0.dist-info/METADATA
bass_model_package-0.1.0.dist-info/WHEEL
bass_model_package-0.1.0.dist-info/top_level.txt
bass_model_package-0.1.0.dist-info/RECORD
