Metadata-Version: 2.1
Name: bass-model-package
Version: 0.1.0
Summary: Python Package for Bass Model
Home-page: https://github.com/ani0813/bass_model_package
Author: Ani Guloyan
Author-email: ani.guloyan.13@gmail.com
Keywords: bass_model_package
Classifier: Development Status :: 2 - Pre-Alpha
Classifier: Intended Audience :: Developers
Classifier: Natural Language :: English
Classifier: Programming Language :: Python :: 3
Classifier: Programming Language :: Python :: 3.6
Classifier: Programming Language :: Python :: 3.7
Classifier: Programming Language :: Python :: 3.8
Requires-Python: >=3.6
License-File: AUTHORS.rst
